{
    "id": 100900,
    "collectionNo": 76,
    "name": "莫德雷德",
    "voices": {
        "0_B010": "啰嗦！",
        "0_B020": "闭嘴！",
        "0_B030": "给我去死！",
        "0_B040": "Take That, You Fiend！",
        "0_B050": "此乃毁灭我父王之邪剑，对吾华丽父王的叛逆！",
        "0_B080": "准备突击咯！",
        "0_B090": "看招！",
        "0_B100": "你可以逃跑哦。 因为你的对手可是我莫德雷德！",
        "0_B110": "真是的。 杂鱼就要像个杂鱼的样子，被我一扫而尽啊！",
        "0_B120": "算啦，你就当倒霉，老老实实放弃吧！",
        "0_B130": "蠢货。就你那样还想挡在父王面前吗？",
        "0_B140": "该死的！",
        "0_B150": "你丫的！",
        "0_B160": "父……王……",
        "0_B170": "该死的，搞砸了……",
        "0_B180": "噢！",
        "0_B190": "交给我吧！",
        "0_B200": "好嘞！",
        "0_B210": "哈，那让我们开始蹂躏吧！",
        "0_B220": "很好，干掉对手！",
        "0_B410": "怎么啦，怎么啦！",
        "0_B440": "让我稍微调教一下你吧！",
        "0_B800": "吾非王，而是步王后尘之人。为了王之安宁，吾要驱逐所有敌人！对吾华丽父王的叛逆！",
        "0_G010": "好，又向父王靠近了一步。",
        "0_G020": "有种插了翅膀的感觉。",
        "0_G030": "没什么大不了的，我强大是理所应当的。",
        "0_G040": "太好了！ 御主，你觉得如何！",
        "0_G050": "谢谢你，御主。 我终于到达了这个境界。",
        "0_H010": "什么嘛，是你出生的日子啊。 好啦好啦，恭喜你还不行吗。",
        "0_H020": "好像出了什么事哦。 来啊来啊，快点快点！",
        "0_H030": "喂～御主。快走啦，快去做任务啦～！",
        "0_H040": "你当然是御主啊，但肯定是我的地位比较高。 有意见吗？",
        "0_H050": "御主，我和你挺合得来的。 嗯，合得来是很关键的。",
        "0_H060": "喜欢的事……兜风吧？你那算啥表情。我很擅长驾驶哦。",
        "0_H070": "讨厌…… 啊，没错。当然是父王啦！",
        "0_H080": "圣杯？ 既然我是最强的，那我自然有得到圣杯的权利。",
        "0_H090": "喂，别乱碰。想被打吗？",
        "0_H100": "别拉我头发啦，你是小鬼头吗！",
        "0_H110": "你个笨蛋御主！我要是不努力的话，你根本无药可救吧！ 真是的，真是的！",
        "0_H120": "我问你啊，你觉得我能成为超越父王的骑士吗？嗯嗯……这样啊！",
        "0_H130": "我将剑托付给你，名誉托付给你，生命奉献给你。或许我只是一名三流骑士，即便如此你也愿意吗？",
        "0_H140": "恶，高文啊。你这家伙为什么总是一副自以为老大哥的样子啦。给我滚一边去啦，你这傻瓜。",
        "0_H150": "兰斯洛特……哎，兰斯洛特啊……尽管我没资格这么说，但你还真好意思若无其事地露面啊！唔？　你那是什么表情？……因为第一次看到我的真面目，所以有些动摇？你这个人……还真是……那啥啊……",
        "0_H160": "噢，优等生啊。不过银臂还真帅啊，借我用用。没关系啦！我会还给你的啦！不会搞坏的啦！",
        "0_H170": "恶，废物Archer崔斯坦！怎么连你也在啊！御主，我劝你还是炒他鱿鱼比较好！……你看，他果然站着睡着了！",
        "0_H180": "骑士王在这里？……不，我不用见她。我的剑托付的对象是你。我不觉得自己不忠到能够同时侍奉两个王哦？",
        "0_H190": "妖精骑士啊。……我呢？　有我的妖精骑士吗？没有？　唔～，反正也没关系啦！没·关·系·啦！",
        "0_H200": "唔？　我想迦勒底怎么吹起了一阵清爽的风，原来是珀西瓦尔啊。啊？　是我啦，莫德雷德。生前一直戴着头盔，你认不出来也在所难免。总之，请多关照啦！",
        "0_H210": "哎，母后……！？不，总觉得印象不太一样呢。唔～，妖精国的母后。……刚才，您不是称呼御主为我的丈夫？哎，你要成为我父王了吗？虽然不愿意但这也太离谱了吧！",
        "0_H5210": "哎，母后……！？不，总觉得印象不太一样呢。唔～，妖精国的母后。……刚才，您不是称呼御主为我的妻子？哎，你要成为我母后了吗？虽然不愿意但这也太离谱了吧！",
        "0_S010": "Saber，莫德雷德驾临。 父王在吗？",
        "11_B010": "粉碎！",
        "11_B020": "绞烂！",
        "11_B030": "别小看我！",
        "11_B040": "你就在那儿睡吧，永远！",
        "11_B080": "真是太棒了！",
        "11_B090": "真拿你没办法！",
        "11_B100": "穿上了这套衣服的我可是比平时强了三倍哦！ 不过我平时就是强了三倍的状态！",
        "11_B110": "好嘞，一个不剩全部打飞！",
        "11_B120": "赢了赢了，凯旋！",
        "11_B130": "好嘞，晚餐吃鸡，御主买单！",
        "11_B150": "嘎……可恶！！",
        "11_B160": "抱歉……我先走一步了……",
        "11_B170": "变得一无所有了吗……可恶……",
        "11_B180": "好！",
        "11_B190": "行嘞！",
        "11_B200": "明白了！",
        "11_B210": "在我的剑下毁灭吧畜生们！",
        "11_B220": "要我手下留情吗，啊？",
        "11_B410": "看招！",
        "11_B440": "没了脑袋应该就会老实点了吗！",
        "11_G010": "好，又向父王靠近了一步。",
        "11_G060": "总而言之，这件衣服如何。很帅吧？是过去某个人为我买的衣服，我还挺喜欢的。反正相当便于行动。春夏秋就穿这个了！",
        "11_H9000": "好不容易脱下了沉重的铠甲。当然要去好好玩个痛快啦。好了，御主，你打算去哪儿？我会陪你去的，真拿你没辙呢！",
        "12_B010": "粉碎！",
        "12_B020": "绞烂！",
        "12_B030": "别小看我！",
        "12_B040": "你就在那儿睡吧，永远！",
        "12_B080": "真是太棒了！",
        "12_B090": "真拿你没办法！",
        "12_B100": "穿上了这套衣服的我可是比平时强了三倍哦！ 不过我平时就是强了三倍的状态！",
        "12_B110": "好嘞，一个不剩全部打飞！",
        "12_B120": "赢了赢了，凯旋！",
        "12_B130": "好嘞，晚餐吃鸡，御主买单！",
        "12_B150": "嘎……可恶！！",
        "12_B160": "抱歉……我先走一步了……",
        "12_B170": "变得一无所有了吗……可恶……",
        "12_B180": "好！",
        "12_B190": "行嘞！",
        "12_B200": "明白了！",
        "12_B210": "在我的剑下毁灭吧畜生们！",
        "12_B220": "要我手下留情吗，啊？",
        "12_B410": "看招！",
        "12_B440": "没了脑袋应该就会老实点了吗！",
        "12_G010": "好，又向父王靠近了一步。",
        "12_G060": "总而言之，这件衣服如何。很帅吧？是过去某个人为我买的衣服，我还挺喜欢的。反正相当便于行动。春夏秋就穿这个了！",
        "12_H9000": "好不容易脱下了沉重的铠甲。当然要去好好玩个痛快啦。好了，御主，你打算去哪儿？我会陪你去的，真拿你没辙呢！"
    },
    "ChrVoice_ids": [
        100900
    ]
}