{
    "id": 505000,
    "collectionNo": 330,
    "name": "玛尔达〔圣诞〕",
    "voices": {
        "0_B010": {
            "name": "攻击 1",
            "text": {
                "0_B010": "变得美味吧～！"
            }
        },
        "0_B020": {
            "name": "攻击 2",
            "text": {
                "0_B020": "嘿咻，咚！"
            }
        },
        "0_B040": {
            "name": "额外攻击 1",
            "text": {
                "0_B040": "唔～嘿，烤好啦！"
            }
        },
        "0_B050": {
            "name": "宝具 1",
            "text": {
                "0_B050": "要开始了哦？",
                "0_B051": "美味的美食，",
                "0_B052": "愉快的派对♪",
                "0_B053": "好！",
                "0_B054": "圣夜的美味佳肴，大家齐愉快享受！"
            }
        },
        "0_B080": {
            "name": "技能 1",
            "text": {
                "0_B080": "给你这个，邀请函！"
            }
        },
        "0_B090": {
            "name": "技能 2",
            "text": {
                "0_B090": "肚子饿不饿？"
            }
        },
        "0_B100": {
            "name": "开始 1",
            "text": {
                "0_B100": "没问题，交给姐姐我吧！"
            }
        },
        "0_B110": {
            "name": "开始 2",
            "text": {
                "0_B110": "或许稍微有些……可怕呢。"
            }
        },
        "0_B120": {
            "name": "胜利 1",
            "text": {
                "0_B120": "咦？　结束了……吗？"
            }
        },
        "0_B130": {
            "name": "胜利 2",
            "text": {
                "0_B130": "烹饪完成！"
            }
        },
        "0_B140": {
            "name": "受击 2",
            "text": {
                "0_B140": "什么嘛！"
            }
        },
        "0_B160": {
            "name": "无法战斗 1",
            "text": {
                "0_B160": "不行……稍微有些累了……"
            }
        },
        "0_B170": {
            "name": "无法战斗 2",
            "text": {
                "0_B170": "得为派对……做准备才行……"
            }
        },
        "0_B180": {
            "name": "指令卡 1",
            "text": {
                "0_B180": "来了～！"
            }
        },
        "0_B190": {
            "name": "指令卡 2",
            "text": {
                "0_B190": "嗯！"
            }
        },
        "0_B200": {
            "name": "指令卡 3",
            "text": {
                "0_B200": "要沉重地上吧？"
            }
        },
        "0_B210": {
            "name": "宝具卡 1",
            "text": {
                "0_B210": "要上了哦，塔拉斯克！"
            }
        },
        "0_B220": {
            "name": "宝具卡 2",
            "text": {
                "0_B220": "塔拉斯克～，过来哦。"
            }
        },
        "0_B230": {
            "name": "宝具卡 3",
            "text": {
                "0_B230": "要振作精神上哦！"
            }
        },
        "0_B250": {
            "name": "宝具卡 4",
            "text": {
                "0_B250": "交给我吧！"
            }
        },
        "0_B410": {
            "name": "攻击 4",
            "text": {
                "0_B410": "对不起啦！"
            }
        },
        "0_B420": {
            "name": "攻击 5",
            "text": {
                "0_B420": "旋转旋转旋转！"
            }
        },
        "0_B440": {
            "name": "额外攻击 2",
            "text": {
                "0_B440": "美味的，面包，完成啦！"
            }
        },
        "0_B480": {
            "name": "技能 3",
            "text": {
                "0_B480": "没事吧？　有没有哪里痛？"
            }
        },
        "0_B490": {
            "name": "技能 4",
            "text": {
                "0_B490": "料理就是体力，好！"
            }
        },
        "0_B500": {
            "name": "开始 3",
            "text": {
                "0_B500": "交给我吧！"
            }
        },
        "0_B510": {
            "name": "开始 4",
            "text": {
                "0_B510": "开始烹饪了哦！"
            }
        },
        "0_B520": {
            "name": "胜利 3",
            "text": {
                "0_B520": "完成啦～，好好品尝美食吧！"
            }
        },
        "0_B530": {
            "name": "胜利 4",
            "text": {
                "0_B530": "还在烹饪着呢，这就结束了……？"
            }
        },
        "0_B540": {
            "name": "受击 4",
            "text": {
                "0_B540": "真是的！"
            }
        },
        "0_B550": {
            "name": "受击 3",
            "text": {
                "0_B550": "怎么了嘛！？"
            }
        },
        "0_B800": {
            "name": "宝具 2",
            "text": {
                "0_B800": "要动手了哦！",
                "0_B801": "倾注心意，",
                "0_B802": "准备派对♪",
                "0_B803": "嗯！",
                "0_B804": "圣夜的美味佳肴，大家齐愉快享受！"
            }
        },
        "0_B840": {
            "name": "额外攻击 3",
            "text": {
                "0_B840": "我可以，做得，非常好吃哦！"
            }
        },
        "0_C010": {
            "name": "Making Christmas Party！ 8",
            "text": {
                "0_C010": "要开始抽了哦！　旋转旋转旋转！ 来，请吧！"
            }
        },
        "0_C020": {
            "name": "Making Christmas Party！ 9",
            "text": {
                "0_C020": "超抽奖！ 哎哎！！"
            }
        },
        "0_C030": {
            "name": "Making Christmas Party！ 10",
            "text": {
                "0_C030": "塔拉斯克也在说要比平时转得更多哦！ 哎，没说？　是吗？ 别管了，快转起来抽吧！"
            }
        },
        "0_C040": {
            "name": "Making Christmas Party！ 11",
            "text": {
                "0_C040": "要注意力度…… 你想，如果动真格转起来感觉会坏嘛…… 哎？　没问题？　很坚固？ 不会嘎吱叫？"
            }
        },
        "0_C050": {
            "name": "Making Christmas Party！ 12",
            "text": {
                "0_C050": "塔拉斯克在左顾右盼呢！ 感觉有什么要来了……！ 手臂，不对，内心有点激动呢！！"
            }
        },
        "0_C060": {
            "name": "Making Christmas Party！ 13",
            "text": {
                "0_C060": "最后的大奖要来了哦！ 准备好了吗？ 哎哎！"
            }
        },
        "0_C110": {
            "name": "Making Christmas Party！ 14",
            "text": {
                "0_C110": "原来里面是这样的呀！ 怎么样，感觉还不错吗？"
            }
        },
        "0_C120": {
            "name": "Making Christmas Party！ 15",
            "text": {
                "0_C120": "公开！ 虽然或许没有中…… 但只要能对你有帮助就好了。"
            }
        },
        "0_C130": {
            "name": "Making Christmas Party！ 16",
            "text": {
                "0_C130": "真可惜！ 虽然不知道有什么可惜的，但真可惜呢！ 好了，继续下一次吧！"
            }
        },
        "0_C140": {
            "name": "Making Christmas Party！ 17",
            "text": {
                "0_C140": "哎～，唔～。 原来如此原来如此。 那要不要抽下一次？"
            }
        },
        "0_C150": {
            "name": "Making Christmas Party！ 18",
            "text": {
                "0_C150": "恭喜！　中大奖啦！ 你看你看，塔拉斯克也很高兴，我也很高兴！ 要不要烤个面包呢！"
            }
        },
        "0_C160": {
            "name": "Making Christmas Party！ 19",
            "text": {
                "0_C160": "最后的大奖！　终于完成了呢…… 嗯嗯，了不起了不起。哎，还没抽够？ 好，我知道了，我也会奉陪到底。 尽情抽吧！"
            }
        },
        "0_G010": {
            "name": "升级 1",
            "text": {
                "0_G010": "唔！",
                "0_G011": "我想到了一个有趣的配方！"
            }
        },
        "0_G020": {
            "name": "灵基再临 2",
            "text": {
                "0_G020": "呵呵，谢谢！",
                "0_G021": "感觉擅长的料理变多了！",
                "0_G022": "比起质，更应该追求量……的说法虽然比较粗暴，但还是得一次做出很多料理才行呢。"
            }
        },
        "0_G030": {
            "name": "灵基再临 1",
            "text": {
                "0_G030": "是叫灵基的……再临吗？",
                "0_G031": "虽然不太懂，但应该是好事吧。"
            }
        },
        "0_G040": {
            "name": "灵基再临 3",
            "text": {
                "0_G040": "臂力是不会提升的，放心，放心！",
                "0_G041": "因为说是圣女嘛，用关节技扣住烂醉的男人让他们老实下来未免太不成体统了吧？",
                "0_G042": "要让人安静下来还是得用美食才行，对吧？"
            }
        },
        "0_G050": {
            "name": "灵基再临 4",
            "text": {
                "0_G050": "该怎么说呢……",
                "0_G051": "现在的我有种无论什么派对都放马过来吧！的感觉。",
                "0_G052": "肯定是多亏了您吧。",
                "0_G053": "谢谢您，御主！"
            }
        },
        "0_G110": {
            "name": "升级 2",
            "text": {
                "0_G110": "唔唔！",
                "0_G111": "持锅时的反抗感……",
                "0_G112": "那个，感觉变得不错了！"
            }
        },
        "0_G120": {
            "name": "升级 3",
            "text": {
                "0_G120": "仿佛变得有精神起来了！"
            }
        },
        "0_H010": {
            "name": "生日",
            "text": {
                "0_H010": "生日快乐！",
                "0_H011": "今晚姐姐我会大展身手为你烹饪美食哦！",
                "0_H012": "呵呵，好好期待吧。",
                "0_H013": "当然，也包括礼物哦。"
            }
        },
        "0_H020": {
            "name": "活动举行中",
            "text": {
                "0_H020": "活动……",
                "0_H021": "是类似宴会那种吧！"
            }
        },
        "0_H030": {
            "name": "对话 1",
            "text": {
                "0_H030": "我们走吧，御主。",
                "0_H031": "得去参加派对才行！"
            }
        },
        "0_H040": {
            "name": "对话 2",
            "text": {
                "0_H040": "御主……御，主……",
                "0_H041": "我是从者，而你是御主吧。",
                "0_H042": "嗯，没问题！",
                "0_H043": "这种我隐约能够理解。"
            }
        },
        "0_H050": {
            "name": "对话 3",
            "text": {
                "0_H050": "御主，肚子饿不饿？",
                "0_H051": "有需要随时对姐姐我说哦。",
                "0_H052": "我会立刻为你做些什么的！"
            }
        },
        "0_H060": {
            "name": "喜欢的东西",
            "text": {
                "0_H060": "喜欢的东西？",
                "0_H061": "烹饪！",
                "0_H062": "呵呵，做各种研究很开心哦！"
            }
        },
        "0_H070": {
            "name": "讨厌的东西",
            "text": {
                "0_H070": "讨厌的东西？",
                "0_H071": "唔～，是什么呢，我不太思考这方面……",
                "0_H072": "啊！　我讨厌食材涨价！　当然啦！"
            }
        },
        "0_H080": {
            "name": "关于圣杯",
            "text": {
                "0_H080": "圣杯……？",
                "0_H081": "那是什么？"
            }
        },
        "0_H090": {
            "name": "牵绊Lv.1",
            "text": {
                "0_H090": "圣诞老人……",
                "0_H091": "虽然不太懂，但我也是那个圣诞老人吧。",
                "0_H092": "既然被托付了这个任务，我当然愿意做！"
            }
        },
        "0_H100": {
            "name": "牵绊Lv.2",
            "text": {
                "0_H100": "我为什么会被选为圣诞老人呢？",
                "0_H101": "或许只是个偶然……",
                "0_H102": "和我是那所谓的圣女有什么关系吗？",
                "0_H103": "唔……"
            }
        },
        "0_H110": {
            "name": "牵绊Lv.3",
            "text": {
                "0_H110": "御主喜欢……圣诞老人吗？",
                "0_H111": "呵呵，这样呀。",
                "0_H112": "不，不用说，光看表情也能看出来。",
                "0_H113": "最喜欢了吧。",
                "0_H114": "哎，是这样啊！"
            }
        },
        "0_H120": {
            "name": "牵绊Lv.4",
            "text": {
                "0_H120": "毕竟是御主喜欢的东西嘛，身为圣诞老人，我总得努力才行！",
                "0_H121": "无论是派对还是礼物，都交给我吧！",
                "0_H122": "怎么样？　我做得像不像圣诞老人？"
            }
        },
        "0_H130": {
            "name": "牵绊Lv.5",
            "text": {
                "0_H130": "如果独自一个人的话……",
                "0_H131": "我肯定不会知道自己是否当好了圣诞老人。",
                "0_H132": "所以，有你在真是太好了。",
                "0_H133": "是真的！"
            }
        },
        "0_H170": {
            "name": "对话 4",
            "text": {
                "0_H170": "嗯嗯……",
                "0_H171": "迦勒底的厨房有各种东西呢。",
                "0_H172": "感谢您告诉我，布狄卡小姐！"
            }
        },
        "0_H180": {
            "name": "对话 5",
            "text": {
                "0_H180": "卫宫先生，卫宫先生！",
                "0_H181": "能帮忙尝一下味道吗？"
            }
        },
        "0_H190": {
            "name": "对话 6",
            "text": {
                "0_H190": "猫咪前辈！",
                "0_H191": "关于这个配方……",
                "0_H192": "啊，请等一下，前辈！"
            }
        },
        "0_H200": {
            "name": "对话 7",
            "text": {
                "0_H200": "小孩子的工作就是多吃一点！",
                "0_H201": "明白了吗？",
                "0_H202": "和姐姐说好了哦！"
            }
        },
        "0_H210": {
            "name": "对话 8",
            "text": {
                "0_H210": "快过来，孩子们！",
                "0_H211": "今天的菜单……竟然是，迦勒底流咖喱饭！",
                "0_H212": "呜哇，反馈真不错！",
                "0_H213": "咖喱饭真的很受小孩子欢迎呢！"
            }
        },
        "0_H220": {
            "name": "对话 9",
            "text": {
                "0_H220": "今天的点心是，特制蛋糕！",
                "0_H221": "好了，孩子们，快去洗手！"
            }
        },
        "0_H230": {
            "name": "对话 10",
            "text": {
                "0_H230": "梵高小姐，您没事吧？",
                "0_H231": "有好好吃饭吗？"
            }
        },
        "0_H240": {
            "name": "对话 11",
            "text": {
                "0_H240": "魔女姐姐……",
                "0_H241": "不对，斯卡哈·斯卡蒂小姐……",
                "0_H242": "不知为什么，我似乎会忍不住……",
                "0_H243": "很想叫那个人为妈妈呢……"
            }
        },
        "0_N010": {
            "name": "Making Christmas Party！ 1",
            "text": {
                "0_N010": "欢迎光临！",
                "0_N011": "这里可以多次转动盒子哦。",
                "0_N012": "为什么要转动盒子呢？",
                "0_N013": "虽然不太明白，但加油吧！"
            }
        },
        "0_N020": {
            "name": "Making Christmas Party！ 2",
            "text": {
                "0_N020": "我是玛尔达。",
                "0_N021": "不对，我是圣诞玛尔达。",
                "0_N022": "让我们创造一个愉快的圣诞节吧！"
            }
        },
        "0_N030": {
            "name": "Making Christmas Party！ 3",
            "text": {
                "0_N030": "圣诞节……",
                "0_N031": "理应知道，但毫无真实感，就像不知道似的。",
                "0_N032": "但是，我知道那是非常重要的日子。",
                "0_N033": "啊啊，对不起。",
                "0_N034": "现在就要转盒子抽奖吧？"
            }
        },
        "0_N040": {
            "name": "Making Christmas Party！ 4",
            "text": {
                "0_N040": "欢迎光临，御主。",
                "0_N041": "我从妈妈……呃，不对，是从斯卡哈·斯卡蒂小姐那里听说了。",
                "0_N042": "在这里将盒子交给你就是迦勒底圣诞老人的工作！"
            }
        },
        "0_N050": {
            "name": "Making Christmas Party！ 5",
            "text": {
                "0_N050": "要记得确认帮助信息和通知栏哦。",
                "0_N051": "里面或许会写着什么重要的东西吧？"
            }
        },
        "0_N060": {
            "name": "Making Christmas Party！ 6",
            "text": {
                "0_N060": "迦勒底的圣诞节也到此结束了吧。",
                "0_N061": "辛苦了！",
                "0_N062": "御主，您玩得还开心吗？",
                "0_N063": "……我吗？",
                "0_N064": "我呀……非常开心，谢谢！",
                "0_N065": "另外……",
                "0_N066": "圣诞快乐！　呵呵！"
            }
        },
        "0_N070": {
            "name": "Making Christmas Party！ 7",
            "text": {
                "0_N070": "有没有转很多次盒子抽奖呢？",
                "0_N071": "看着你努力的身影，就会担心、紧张，还会兴奋。",
                "0_N072": "希望你不要输，希望你要努力。",
                "0_N073": "传达到了？",
                "0_N074": "呵呵，哪怕能帮到你一点，我也很高兴！",
                "0_N075": "今后也要努力，我会为你加油的！"
            }
        },
        "0_S010": {
            "name": "召唤",
            "text": {
                "0_S010": "那我重新自我介绍一下……",
                "0_S011": "我是玛尔达。",
                "0_S012": "是圣诞老人玛尔达哦。",
                "0_S013": "从今往后要和我，以及原来灵基的我好好相处哦！"
            }
        },
        "0_S020": {
            "name": "期间限定加入",
            "text": {
                "0_S020": "我是玛尔达。",
                "0_S021": "不对，是圣诞老人玛尔达——",
                "0_S022": "是这样吧？",
                "0_S023": "擅长烹饪和裁缝和……",
                "0_S024": "哎，战斗？　那是什么？",
                "0_S025": "那个，总之，请多关照。",
                "0_S026": "让我们创造一个愉快的圣诞节吧，御主！"
            }
        }
    },
    "ChrVoice_ids": [
        "505000"
    ]
}